.directory
.gitignore
.project
.pydevproject
LICENSE
MANIFEST.in
Makefile
README.md
README.rst
README2.rst
__init__.py
requirements.txt
setup.cfg
setup.py
OGN_Flogger.egg-info/PKG-INFO
OGN_Flogger.egg-info/SOURCES.txt
OGN_Flogger.egg-info/dependency_links.txt
OGN_Flogger.egg-info/not-zip-safe
OGN_Flogger.egg-info/requires.txt
OGN_Flogger.egg-info/top_level.txt
data/flogger.ui
data/flogger_about.ui
data/flogger_config_1.ui
data/flogger_help.ui
data/flogger_help_icon-1.png
data/flogger_icon-08.png
data/flogger_resources.qrc
data/flogger_schema-1.0.4.sql
data/flogger_settings_file.txt
data/flogger_start.png
data/flogger_stop.png
data/ogn-logo-ani.gif
src/__init__.py
src/flarm_db.py
src/flogger.ui.py
src/flogger3.py
src/flogger_OGN_db.py
src/flogger_aprs_parser.py
src/flogger_dump_IGC.py
src/flogger_dump_flights.py
src/flogger_dump_tracks.py
src/flogger_email_log.py
src/flogger_email_msg.py
src/flogger_find_tug.py
src/flogger_functions.py
src/flogger_get_coords.py
src/flogger_gui.py
src/flogger_landout.py
src/flogger_moviesplash.py
src/flogger_path_join.py
src/flogger_process_log.py
src/flogger_process_log_V1.py
src/flogger_process_log_old.py
src/flogger_resources_rc.py
src/flogger_settings.py
src/flogger_signals.py
src/flogger_splash.py
src/flogger_test_YorN.py
src/flogger_ui.py
src/gpxTracks.py
src/open_db.py