Metadata-Version: 1.2
Name: OGN-Flogger
Version: 0.3.2a14
Summary: Realtime logging of glider flights from Flarm data
Home-page: http://github.com/tobiz/OGN-Flogger
Author: tobiz
Author-email: pjrobinson@metronet.co.uk
License: GPL
Project-URL: tracker, http://github.com/tobiz/OGN-Flogger/issues
Keywords: OGN Open Glider Flarm Logging Tracking
Platform: UNKNOWN
Classifier: Development Status :: 3 - Alpha
Classifier: License :: OSI Approved :: GNU General Public License (GPL)
Classifier: Programming Language :: Python :: 2.7
Classifier: Topic :: Scientific/Engineering :: Information Analysis
Requires-Python: >=2.7, <3
